RobotSlackNotification/__init__.py
RobotSlackNotification/messages.py
robotframework_slacknotification-0.1.7.dist-info/LICENSE
robotframework_slacknotification-0.1.7.dist-info/METADATA
robotframework_slacknotification-0.1.7.dist-info/WHEEL
robotframework_slacknotification-0.1.7.dist-info/RECORD
