Metadata-Version: 2.3
Name: robotframework-slacknotification
Version: 0.1.7
Summary: Send real-time notifications to Slack with the results of your tests
License: Apache-2.0 license
Author: Robot Courses
Author-email: git@robotcourses.com.br
Requires-Python: >=3.9
Classifier: Development Status :: 5 - Production/Stable
Classifier: Operating System :: OS Independent
Classifier: Topic :: Software Development :: Quality Assurance
Classifier: Topic :: Software Development :: Testing
Classifier: Programming Language :: Python
Classifier: Programming Language :: Python :: 3.8
Classifier: Framework :: Robot Framework
Classifier: Framework :: Robot Framework :: Library
Requires-Dist: python-dotenv (>=1.1.0,<2.0.0)
Requires-Dist: robotframework (>=7.0,<8.0)
Requires-Dist: slack-sdk (>=3.35.0,<4.0.0)
Project-URL: Bugs Tracker, https://github.com/robotcourses/robotframework-slacknotification/issues
Project-URL: Github, https://github.com/robotcourses/robotframework-slacknotification
